Metadata-Version: 2.1
Name: pytest-pokie
Version: 0.3.0
Summary: Pokie plugin for pytest
Home-page: https://git.oddbit.org/OddBit/pytest-pokie
Author: Joao Pinheiro
License: BSD-2-Clause
Project-URL: Source, https://git.oddbit.org/OddBit/pytest-pokie
Classifier: Development Status :: 5 - Production/Stable
Classifier: Intended Audience :: Developers
Classifier: License :: OSI Approved :: BSD License
Classifier: Operating System :: OS Independent
Classifier: Programming Language :: Python :: 3.8
Classifier: Programming Language :: Python :: 3.9
Classifier: Programming Language :: Python :: 3.10
Classifier: Programming Language :: Python :: 3.11
Classifier: Programming Language :: Python :: Implementation :: CPython
Classifier: Programming Language :: Python :: Implementation :: PyPy
Classifier: Topic :: Software Development :: Testing
Requires-Python: >=3.8
License-File: LICENSE
